[{"model": "admin.logentry", "pk": 1, "fields": {"action_time": "2025-06-06T05:43:39.597Z", "user": 1, "content_type": 6, "object_id": "2", "object_repr": "taxi_admin", "action_flag": 2, "change_message": "[{\"changed\": {\"fields\": [\"Superuser status\", \"User permissions\"]}}]"}}, {"model": "admin.logentry", "pk": 2, "fields": {"action_time": "2025-06-06T05:43:50.276Z", "user": 1, "content_type": 6, "object_id": "2", "object_repr": "taxi_admin", "action_flag": 2, "change_message": "[]"}}, {"model": "auth.permission", "pk": 1, "fields": {"name": "Can add log entry", "content_type": 1, "codename": "add_logentry"}}, {"model": "auth.permission", "pk": 2, "fields": {"name": "Can change log entry", "content_type": 1, "codename": "change_logentry"}}, {"model": "auth.permission", "pk": 3, "fields": {"name": "Can delete log entry", "content_type": 1, "codename": "delete_logentry"}}, {"model": "auth.permission", "pk": 4, "fields": {"name": "Can view log entry", "content_type": 1, "codename": "view_logentry"}}, {"model": "auth.permission", "pk": 5, "fields": {"name": "Can add permission", "content_type": 2, "codename": "add_permission"}}, {"model": "auth.permission", "pk": 6, "fields": {"name": "Can change permission", "content_type": 2, "codename": "change_permission"}}, {"model": "auth.permission", "pk": 7, "fields": {"name": "Can delete permission", "content_type": 2, "codename": "delete_permission"}}, {"model": "auth.permission", "pk": 8, "fields": {"name": "Can view permission", "content_type": 2, "codename": "view_permission"}}, {"model": "auth.permission", "pk": 9, "fields": {"name": "Can add group", "content_type": 3, "codename": "add_group"}}, {"model": "auth.permission", "pk": 10, "fields": {"name": "Can change group", "content_type": 3, "codename": "change_group"}}, {"model": "auth.permission", "pk": 11, "fields": {"name": "Can delete group", "content_type": 3, "codename": "delete_group"}}, {"model": "auth.permission", "pk": 12, "fields": {"name": "Can view group", "content_type": 3, "codename": "view_group"}}, {"model": "auth.permission", "pk": 13, "fields": {"name": "Can add content type", "content_type": 4, "codename": "add_contenttype"}}, {"model": "auth.permission", "pk": 14, "fields": {"name": "Can change content type", "content_type": 4, "codename": "change_contenttype"}}, {"model": "auth.permission", "pk": 15, "fields": {"name": "Can delete content type", "content_type": 4, "codename": "delete_contenttype"}}, {"model": "auth.permission", "pk": 16, "fields": {"name": "Can view content type", "content_type": 4, "codename": "view_contenttype"}}, {"model": "auth.permission", "pk": 17, "fields": {"name": "Can add session", "content_type": 5, "codename": "add_session"}}, {"model": "auth.permission", "pk": 18, "fields": {"name": "Can change session", "content_type": 5, "codename": "change_session"}}, {"model": "auth.permission", "pk": 19, "fields": {"name": "Can delete session", "content_type": 5, "codename": "delete_session"}}, {"model": "auth.permission", "pk": 20, "fields": {"name": "Can view session", "content_type": 5, "codename": "view_session"}}, {"model": "auth.permission", "pk": 21, "fields": {"name": "Can add user", "content_type": 6, "codename": "add_user"}}, {"model": "auth.permission", "pk": 22, "fields": {"name": "Can change user", "content_type": 6, "codename": "change_user"}}, {"model": "auth.permission", "pk": 23, "fields": {"name": "Can delete user", "content_type": 6, "codename": "delete_user"}}, {"model": "auth.permission", "pk": 24, "fields": {"name": "Can view user", "content_type": 6, "codename": "view_user"}}, {"model": "auth.permission", "pk": 25, "fields": {"name": "Can add Telegram User", "content_type": 7, "codename": "add_telegramusers"}}, {"model": "auth.permission", "pk": 26, "fields": {"name": "Can change Telegram User", "content_type": 7, "codename": "change_telegramusers"}}, {"model": "auth.permission", "pk": 27, "fields": {"name": "Can delete Telegram User", "content_type": 7, "codename": "delete_telegramusers"}}, {"model": "auth.permission", "pk": 28, "fields": {"name": "Can view Telegram User", "content_type": 7, "codename": "view_telegramusers"}}, {"model": "auth.permission", "pk": 29, "fields": {"name": "Can add Offer", "content_type": 8, "codename": "add_offers"}}, {"model": "auth.permission", "pk": 30, "fields": {"name": "Can change Offer", "content_type": 8, "codename": "change_offers"}}, {"model": "auth.permission", "pk": 31, "fields": {"name": "Can delete Offer", "content_type": 8, "codename": "delete_offers"}}, {"model": "auth.permission", "pk": 32, "fields": {"name": "Can view Offer", "content_type": 8, "codename": "view_offers"}}, {"model": "auth.permission", "pk": 33, "fields": {"name": "Can add Driver", "content_type": 9, "codename": "add_drivers"}}, {"model": "auth.permission", "pk": 34, "fields": {"name": "Can change Driver", "content_type": 9, "codename": "change_drivers"}}, {"model": "auth.permission", "pk": 35, "fields": {"name": "Can delete Driver", "content_type": 9, "codename": "delete_drivers"}}, {"model": "auth.permission", "pk": 36, "fields": {"name": "Can view Driver", "content_type": 9, "codename": "view_drivers"}}, {"model": "contenttypes.contenttype", "pk": 1, "fields": {"app_label": "admin", "model": "logentry"}}, {"model": "contenttypes.contenttype", "pk": 2, "fields": {"app_label": "auth", "model": "permission"}}, {"model": "contenttypes.contenttype", "pk": 3, "fields": {"app_label": "auth", "model": "group"}}, {"model": "contenttypes.contenttype", "pk": 4, "fields": {"app_label": "contenttypes", "model": "contenttype"}}, {"model": "contenttypes.contenttype", "pk": 5, "fields": {"app_label": "sessions", "model": "session"}}, {"model": "contenttypes.contenttype", "pk": 6, "fields": {"app_label": "users", "model": "user"}}, {"model": "contenttypes.contenttype", "pk": 7, "fields": {"app_label": "telegram_users", "model": "telegramusers"}}, {"model": "contenttypes.contenttype", "pk": 8, "fields": {"app_label": "offers", "model": "offers"}}, {"model": "contenttypes.contenttype", "pk": 9, "fields": {"app_label": "drivers", "model": "drivers"}}, {"model": "sessions.session", "pk": "fs8tnw0myq557wvj8vv0zksq34qtj5uz", "fields": {"session_data": ".eJxVjMsOwiAQRf-FtSHlPbh07zeQgQGpGkhKuzL-uzbpQrf3nHNfLOC21rCNvISZ2JkJdvrdIqZHbjugO7Zb56m3dZkj3xV-0MGvnfLzcrh_BxVH_dbGCZKA5EHA5JKT3qtsAFTRHp2yGAGIjBKyOB21chDJAkWaRCErFHt_AL42NzI:1uVqo7:kjNzvocFGObj0SRDfkWUN8xqYQUGCFcJ3YX6MyNdse0", "expire_date": "2025-07-13T12:06:51.532Z"}}, {"model": "sessions.session", "pk": "g2zgre87rh5tx4kmbygk9a4frz2p8xeb", "fields": {"session_data": ".eJxVjMsOwiAQRf-FtSHlPbh07zeQgQGpGkhKuzL-uzbpQrf3nHNfLOC21rCNvISZ2JkJdvrdIqZHbjugO7Zb56m3dZkj3xV-0MGvnfLzcrh_BxVH_dbGCZKA5EHA5JKT3qtsAFTRHp2yGAGIjBKyOB21chDJAkWaRCErFHt_AL42NzI:1uNPqd:2wuqTjKTNr1TD-kTH3522cJNe8o-Y4Rc8WUjTkJ8awk", "expire_date": "2025-06-20T05:42:35.625Z"}}, {"model": "sessions.session", "pk": "mx7c9lkw4m0inhukc43g1x4zc631e507", "fields": {"session_data": ".eJxVjMEOwiAQBf-FsyFCgQWP3vsNZIFFqgaS0p6M_64kPeh1Zt57MY_7VvzeafVLYhcm2emXBYwPqkOkO9Zb47HVbV0CHwk_bOdzS_S8Hu3fQcFevmvEnLQVmeAMWk5SCwUA1giYJkVGoUQXHIKOKRoKKIIL5ISBwa3M7P0B0Ss3sA:1uNPsH:FowoxKSra8A91hDPZJenbEXrY469OhsaQadjhYbR_1M", "expire_date": "2025-06-20T05:44:17.495Z"}}, {"model": "sessions.session", "pk": "p3wxkityikbkavllp9117hf86orgpj4t", "fields": {"session_data": ".eJxVjMsOwiAQRf-FtSHlPbh07zeQgQGpGkhKuzL-uzbpQrf3nHNfLOC21rCNvISZ2JkJdvrdIqZHbjugO7Zb56m3dZkj3xV-0MGvnfLzcrh_BxVH_dbGCZKA5EHA5JKT3qtsAFTRHp2yGAGIjBKyOB21chDJAkWaRCErFHt_AL42NzI:1uWTNv:xFIZiXvYY9h0hQ1kEFSJdvbiDGpHBI0AWIEgXtw3Ud4", "expire_date": "2025-07-15T05:18:23.372Z"}}, {"model": "users.user", "pk": 1, "fields": {"password": "pbkdf2_sha256$720000$t6zg5CGUnCLGt0FwUACFzK$OubHtaUPDifKtQPQSKMMYFEbIYqNUI6YOao82AuLfVU=", "last_login": "2025-07-01T05:18:23.363Z", "is_superuser": true, "full_name": "Muhammad Nur", "created_at": "2025-06-06T05:41:26.768Z", "updated_at": "2025-06-06T05:41:26.768Z", "is_active": true, "is_staff": true, "groups": [], "user_permissions": []}}, {"model": "users.user", "pk": 2, "fields": {"password": "pbkdf2_sha256$720000$qxztyFWzgP3VZvp5J7XUA8$NCrmDM8uxDl/gXwrYfvacZkT0aChUGF+cOCBGKRhjAE=", "last_login": "2025-06-06T05:44:17.492Z", "is_superuser": false, "full_name": "taxi_admin", "created_at": "2025-06-06T05:41:53.771Z", "updated_at": "2025-06-06T05:43:50.272Z", "is_active": true, "is_staff": true, "groups": [], "user_permissions": [33, 34, 35, 36, 29, 30, 31, 32, 28]}}, {"model": "telegram_users.telegramusers", "pk": 1, "fields": {"chat_id": "1974800905", "username": "TheMuhammadNur", "full_name": "Muhammad Nur Suxbatullayev", "language": "uz", "created_at": "2025-06-06T05:47:18.560Z", "updated_at": "2025-07-01T05:19:48.819Z"}}, {"model": "telegram_users.telegramusers", "pk": 2, "fields": {"chat_id": "5878869082", "username": null, "full_name": "Deleted Account", "language": "uz", "created_at": "2025-06-06T05:49:46.775Z", "updated_at": "2025-06-13T12:59:58.932Z"}}, {"model": "telegram_users.telegramusers", "pk": 3, "fields": {"chat_id": "725168806", "username": "Raximjon863", "full_name": "Рахимжон", "language": "uz", "created_at": "2025-06-06T05:52:03.909Z", "updated_at": "2025-06-19T16:08:56.197Z"}}, {"model": "telegram_users.telegramusers", "pk": 4, "fields": {"chat_id": "5129125910", "username": "Saloxiddin130", "full_name": "Saloxiddin", "language": "uz", "created_at": "2025-06-06T13:21:20.254Z", "updated_at": "2025-06-06T13:21:20.254Z"}}, {"model": "telegram_users.telegramusers", "pk": 5, "fields": {"chat_id": "7989208827", "username": "Doston_Fakhriddinovich", "full_name": "Doston_Fakhriddinovich", "language": "uz", "created_at": "2025-06-06T19:26:51.794Z", "updated_at": "2025-06-06T19:26:51.794Z"}}, {"model": "telegram_users.telegramusers", "pk": 6, "fields": {"chat_id": "7701643765", "username": null, "full_name": "sher sam", "language": "uz", "created_at": "2025-06-06T19:36:32.132Z", "updated_at": "2025-06-06T19:36:32.132Z"}}, {"model": "telegram_users.telegramusers", "pk": 7, "fields": {"chat_id": "910224315", "username": null, "full_name": "Shodiyorjon Turaev", "language": "uz", "created_at": "2025-06-06T20:49:06.534Z", "updated_at": "2025-06-06T20:49:06.535Z"}}, {"model": "telegram_users.telegramusers", "pk": 8, "fields": {"chat_id": "7026163087", "username": "navruz_673", "full_name": "Navruz", "language": "uz", "created_at": "2025-06-06T22:22:48.028Z", "updated_at": "2025-06-06T22:22:48.028Z"}}, {"model": "telegram_users.telegramusers", "pk": 9, "fields": {"chat_id": "6790333950", "username": null, "full_name": "Suhrob Kabulov", "language": "uz", "created_at": "2025-06-08T03:35:44.010Z", "updated_at": "2025-06-08T03:35:44.010Z"}}, {"model": "telegram_users.telegramusers", "pk": 10, "fields": {"chat_id": "6806750685", "username": "Oydin_06_02_24", "full_name": "202_IAS_ Miss_Mohina", "language": "uz", "created_at": "2025-06-08T12:54:22.615Z", "updated_at": "2025-06-08T12:54:22.615Z"}}, {"model": "telegram_users.telegramusers", "pk": 11, "fields": {"chat_id": "6678960554", "username": null, "full_name": "🫶🏻💋", "language": "uz", "created_at": "2025-06-10T02:54:43.656Z", "updated_at": "2025-06-10T02:54:43.656Z"}}, {"model": "telegram_users.telegramusers", "pk": 12, "fields": {"chat_id": "8141689375", "username": "TafSoftuz", "full_name": "TafSoft Admin", "language": "uz", "created_at": "2025-06-10T07:41:44.890Z", "updated_at": "2025-06-10T07:41:44.890Z"}}, {"model": "telegram_users.telegramusers", "pk": 13, "fields": {"chat_id": "733784514", "username": "Realmadred00", "full_name": ".", "language": "uz", "created_at": "2025-06-10T16:25:05.034Z", "updated_at": "2025-06-10T16:25:05.034Z"}}, {"model": "telegram_users.telegramusers", "pk": 14, "fields": {"chat_id": "5179062164", "username": null, "full_name": "СУННАТ", "language": "uz", "created_at": "2025-06-13T18:07:46.442Z", "updated_at": "2025-06-13T18:07:46.442Z"}}, {"model": "telegram_users.telegramusers", "pk": 15, "fields": {"chat_id": "977975198", "username": "DOSTON_ALI_007", "full_name": "DOSTON", "language": "uz", "created_at": "2025-06-19T17:27:31.532Z", "updated_at": "2025-06-19T17:27:31.532Z"}}, {"model": "telegram_users.telegramusers", "pk": 16, "fields": {"chat_id": "283745592", "username": null, "full_name": "Qodir Nematov", "language": "uz", "created_at": "2025-06-19T17:32:57.277Z", "updated_at": "2025-06-19T17:32:57.277Z"}}, {"model": "telegram_users.telegramusers", "pk": 17, "fields": {"chat_id": "6829979710", "username": null, "full_name": "Меха 0007", "language": "uz", "created_at": "2025-06-19T18:30:33.251Z", "updated_at": "2025-06-19T18:30:33.251Z"}}, {"model": "telegram_users.telegramusers", "pk": 18, "fields": {"chat_id": "1976715896", "username": null, "full_name": "Asadbek Allayorov", "language": "uz", "created_at": "2025-06-20T04:29:17.306Z", "updated_at": "2025-06-20T04:29:17.307Z"}}, {"model": "telegram_users.telegramusers", "pk": 19, "fields": {"chat_id": "5039939212", "username": "bek_0838", "full_name": "✊FAYZULLAYEV✊", "language": "uz", "created_at": "2025-06-20T18:15:01.518Z", "updated_at": "2025-06-20T18:15:01.518Z"}}, {"model": "telegram_users.telegramusers", "pk": 20, "fields": {"chat_id": "454081678", "username": null, "full_name": "САНЖАР", "language": "uz", "created_at": "2025-06-20T18:29:22.206Z", "updated_at": "2025-06-20T18:29:22.206Z"}}, {"model": "telegram_users.telegramusers", "pk": 21, "fields": {"chat_id": "5733501652", "username": null, "full_name": "Iskandar", "language": "uz", "created_at": "2025-06-21T18:57:51.870Z", "updated_at": "2025-06-21T18:57:51.870Z"}}, {"model": "telegram_users.telegramusers", "pk": 22, "fields": {"chat_id": "7685854816", "username": null, "full_name": "✊✊", "language": "uz", "created_at": "2025-06-22T00:04:56.871Z", "updated_at": "2025-06-22T00:04:56.871Z"}}, {"model": "telegram_users.telegramusers", "pk": 23, "fields": {"chat_id": "7651092875", "username": null, "full_name": "Ok", "language": "uz", "created_at": "2025-06-22T06:36:51.975Z", "updated_at": "2025-06-22T06:36:51.975Z"}}, {"model": "telegram_users.telegramusers", "pk": 24, "fields": {"chat_id": "6127577896", "username": null, "full_name": "Sherzod Fayziyev", "language": "uz", "created_at": "2025-06-22T10:51:50.093Z", "updated_at": "2025-06-22T10:51:50.093Z"}}, {"model": "telegram_users.telegramusers", "pk": 25, "fields": {"chat_id": "5161112272", "username": "toshkentmebel0101", "full_name": "Unnamed Person", "language": "uz", "created_at": "2025-06-22T17:39:43.959Z", "updated_at": "2025-06-22T17:39:43.960Z"}}, {"model": "telegram_users.telegramusers", "pk": 26, "fields": {"chat_id": "467185059", "username": null, "full_name": "Jamshiddin", "language": "uz", "created_at": "2025-06-23T10:37:39.531Z", "updated_at": "2025-06-23T10:37:39.531Z"}}, {"model": "telegram_users.telegramusers", "pk": 27, "fields": {"chat_id": "1110030752", "username": "Jurala83238", "full_name": "Avaz Aka", "language": "uz", "created_at": "2025-06-25T03:32:18.431Z", "updated_at": "2025-06-25T03:32:18.431Z"}}, {"model": "telegram_users.telegramusers", "pk": 28, "fields": {"chat_id": "5999886087", "username": "Dilshodman89", "full_name": "DILSHODMAN", "language": "uz", "created_at": "2025-06-26T05:25:11.093Z", "updated_at": "2025-06-26T05:25:11.093Z"}}, {"model": "telegram_users.telegramusers", "pk": 29, "fields": {"chat_id": "931545199", "username": "Sh885774945", "full_name": "Erbutayev Sherzod Utkirovich", "language": "uz", "created_at": "2025-06-27T07:48:17.282Z", "updated_at": "2025-06-27T07:48:17.282Z"}}, {"model": "telegram_users.telegramusers", "pk": 30, "fields": {"chat_id": "6362840176", "username": null, "full_name": "Dilshod", "language": "uz", "created_at": "2025-06-28T13:12:22.126Z", "updated_at": "2025-06-28T13:12:22.126Z"}}, {"model": "telegram_users.telegramusers", "pk": 31, "fields": {"chat_id": "405659740", "username": null, "full_name": "SDV ŞFK", "language": "uz", "created_at": "2025-06-29T04:27:32.024Z", "updated_at": "2025-06-29T04:27:32.024Z"}}, {"model": "telegram_users.telegramusers", "pk": 32, "fields": {"chat_id": "61260346", "username": "Diyorkhuja", "full_name": "Diyorkhuja Shukurov", "language": "uz", "created_at": "2025-06-30T13:58:21.180Z", "updated_at": "2025-06-30T13:58:21.180Z"}}, {"model": "telegram_users.telegramusers", "pk": 33, "fields": {"chat_id": "5456074061", "username": "Ochilov_Diyor", "full_name": "Diyor Ochilov", "language": "uz", "created_at": "2025-07-01T04:30:30.185Z", "updated_at": "2025-07-01T04:30:30.185Z"}}, {"model": "telegram_users.telegramusers", "pk": 34, "fields": {"chat_id": "6597621564", "username": null, "full_name": "Юсупов Мақсуд Халмирзаевич Максуд", "language": "uz", "created_at": "2025-07-01T05:28:47.346Z", "updated_at": "2025-07-02T14:57:42.013Z"}}, {"model": "telegram_users.telegramusers", "pk": 35, "fields": {"chat_id": "7918761172", "username": "Xayotimguzal", "full_name": "❤️❤️❤️", "language": "uz", "created_at": "2025-07-01T10:08:26.982Z", "updated_at": "2025-07-01T10:08:26.982Z"}}, {"model": "telegram_users.telegramusers", "pk": 36, "fields": {"chat_id": "5046532768", "username": "Mittorn", "full_name": "A", "language": "uz", "created_at": "2025-07-01T13:11:52.825Z", "updated_at": "2025-07-01T13:11:52.825Z"}}, {"model": "telegram_users.telegramusers", "pk": 37, "fields": {"chat_id": "515007330", "username": null, "full_name": "Aziz Kayumov", "language": "uz", "created_at": "2025-07-02T08:19:45.785Z", "updated_at": "2025-07-02T08:19:45.785Z"}}, {"model": "offers.offers", "pk": 1, "fields": {"chat_id": "725168806", "full_name": "Рахимжон", "delivery_address": "tashkent-samarkand", "offer_type": "passenger", "number_of_passengers": "4", "phone_number": "998935365985", "created_at": "2025-06-06T05:48:38.760Z", "updated_at": "2025-06-06T05:48:38.760Z"}}, {"model": "offers.offers", "pk": 2, "fields": {"chat_id": "1974800905", "full_name": "Muhammad Nur Suxbatullayev", "delivery_address": "tashkent-samarkand", "offer_type": "mail", "number_of_passengers": null, "phone_number": "+998900689295", "created_at": "2025-06-06T05:48:40.761Z", "updated_at": "2025-06-06T05:48:40.761Z"}}, {"model": "offers.offers", "pk": 3, "fields": {"chat_id": "5129125910", "full_name": "Saloxiddin", "delivery_address": "tashkent-samarkand", "offer_type": "passenger", "number_of_passengers": "1", "phone_number": "+998957077406", "created_at": "2025-06-06T13:21:41.237Z", "updated_at": "2025-06-06T13:21:41.237Z"}}, {"model": "offers.offers", "pk": 4, "fields": {"chat_id": "7701643765", "full_name": "sher sam", "delivery_address": "samarkand-tashkent", "offer_type": "passenger", "number_of_passengers": "2", "phone_number": "998994999805", "created_at": "2025-06-06T19:36:41.672Z", "updated_at": "2025-06-06T19:36:41.672Z"}}, {"model": "offers.offers", "pk": 5, "fields": {"chat_id": "6806750685", "full_name": "202_IAS_ Miss_Mohina", "delivery_address": "samarkand-tashkent", "offer_type": "passenger", "number_of_passengers": "1", "phone_number": "998770212135", "created_at": "2025-06-08T12:54:36.435Z", "updated_at": "2025-06-08T12:54:36.435Z"}}, {"model": "offers.offers", "pk": 6, "fields": {"chat_id": "910224315", "full_name": "Shodiyorjon Turaev", "delivery_address": "samarkand-tashkent", "offer_type": "mail", "number_of_passengers": null, "phone_number": "+998938353735", "created_at": "2025-06-09T14:12:15.495Z", "updated_at": "2025-06-09T14:12:15.495Z"}}, {"model": "offers.offers", "pk": 7, "fields": {"chat_id": "8141689375", "full_name": "TafSoft Admin", "delivery_address": "tashkent-samarkand", "offer_type": "passenger", "number_of_passengers": "1", "phone_number": "+998905352142", "created_at": "2025-06-10T07:41:53.575Z", "updated_at": "2025-06-10T07:41:53.575Z"}}, {"model": "offers.offers", "pk": 8, "fields": {"chat_id": "733784514", "full_name": ".", "delivery_address": "samarkand-tashkent", "offer_type": "passenger", "number_of_passengers": "1", "phone_number": "+998942884008", "created_at": "2025-06-10T16:28:23.426Z", "updated_at": "2025-06-10T16:28:23.426Z"}}, {"model": "offers.offers", "pk": 9, "fields": {"chat_id": "733784514", "full_name": ".", "delivery_address": "samarkand-tashkent", "offer_type": "passenger", "number_of_passengers": "1", "phone_number": "998942884008", "created_at": "2025-06-10T16:45:39.177Z", "updated_at": "2025-06-10T16:45:39.177Z"}}, {"model": "offers.offers", "pk": 10, "fields": {"chat_id": "733784514", "full_name": ".", "delivery_address": "samarkand-tashkent", "offer_type": "passenger", "number_of_passengers": "1", "phone_number": "+998942884008", "created_at": "2025-06-10T16:46:15.743Z", "updated_at": "2025-06-10T16:46:15.743Z"}}, {"model": "offers.offers", "pk": 11, "fields": {"chat_id": "733784514", "full_name": ".", "delivery_address": "tashkent-samarkand", "offer_type": "passenger", "number_of_passengers": "1", "phone_number": "+998942884008", "created_at": "2025-06-11T12:19:17.369Z", "updated_at": "2025-06-11T12:19:17.369Z"}}, {"model": "offers.offers", "pk": 12, "fields": {"chat_id": "1974800905", "full_name": "Muhammad Nur Suxbatullayev", "delivery_address": "tashkent-samarkand", "offer_type": "passenger", "number_of_passengers": "3", "phone_number": "+998900689295", "created_at": "2025-06-19T16:07:45.956Z", "updated_at": "2025-06-19T16:07:45.956Z"}}, {"model": "offers.offers", "pk": 13, "fields": {"chat_id": "1974800905", "full_name": "Muhammad Nur Suxbatullayev", "delivery_address": "samarkand-tashkent", "offer_type": "passenger", "number_of_passengers": "1", "phone_number": "+998900689295", "created_at": "2025-06-19T16:08:30.930Z", "updated_at": "2025-06-19T16:08:30.930Z"}}, {"model": "offers.offers", "pk": 14, "fields": {"chat_id": "725168806", "full_name": "Рахимжон", "delivery_address": "tashkent-samarkand", "offer_type": "passenger", "number_of_passengers": "4", "phone_number": "998935365985", "created_at": "2025-06-19T16:09:04.462Z", "updated_at": "2025-06-19T16:09:04.462Z"}}, {"model": "offers.offers", "pk": 15, "fields": {"chat_id": "1974800905", "full_name": "Muhammad Nur Suxbatullayev", "delivery_address": "tashkent-samarkand", "offer_type": "passenger", "number_of_passengers": "3", "phone_number": "+998900689295", "created_at": "2025-06-19T16:16:34.099Z", "updated_at": "2025-06-19T16:16:34.099Z"}}, {"model": "offers.offers", "pk": 48, "fields": {"chat_id": "1974800905", "full_name": "Muhammad Nur Suxbatullayev", "delivery_address": "tashkent-samarkand", "offer_type": "passenger", "number_of_passengers": "3", "phone_number": "+998900689295", "created_at": "2025-06-19T16:23:52.977Z", "updated_at": "2025-06-19T16:23:52.977Z"}}, {"model": "offers.offers", "pk": 49, "fields": {"chat_id": "725168806", "full_name": "Рахимжон", "delivery_address": "samarkand-tashkent", "offer_type": "passenger", "number_of_passengers": "2", "phone_number": "998935365985", "created_at": "2025-06-20T01:34:46.182Z", "updated_at": "2025-06-20T01:34:46.182Z"}}, {"model": "offers.offers", "pk": 50, "fields": {"chat_id": "725168806", "full_name": "Рахимжон", "delivery_address": "samarkand-tashkent", "offer_type": "passenger", "number_of_passengers": "4", "phone_number": "998935365985", "created_at": "2025-06-20T12:44:03.938Z", "updated_at": "2025-06-20T12:44:03.938Z"}}, {"model": "offers.offers", "pk": 51, "fields": {"chat_id": "5039939212", "full_name": "✊FAYZULLAYEV✊", "delivery_address": "tashkent-samarkand", "offer_type": "passenger", "number_of_passengers": "3", "phone_number": "+998951820423", "created_at": "2025-06-20T18:16:42.103Z", "updated_at": "2025-06-20T18:16:42.103Z"}}, {"model": "offers.offers", "pk": 52, "fields": {"chat_id": "5039939212", "full_name": "✊FAYZULLAYEV✊", "delivery_address": "tashkent-samarkand", "offer_type": "mail", "number_of_passengers": null, "phone_number": "+998951820423", "created_at": "2025-06-20T18:17:06.090Z", "updated_at": "2025-06-20T18:17:06.090Z"}}, {"model": "offers.offers", "pk": 53, "fields": {"chat_id": "1974800905", "full_name": "Muhammad Nur Suxbatullayev", "delivery_address": "tashkent-samarkand", "offer_type": "passenger", "number_of_passengers": "1", "phone_number": "+998900689295", "created_at": "2025-06-21T05:31:06.781Z", "updated_at": "2025-06-21T05:31:06.781Z"}}, {"model": "offers.offers", "pk": 54, "fields": {"chat_id": "1974800905", "full_name": "Muhammad Nur Suxbatullayev", "delivery_address": "samarkand-tashkent", "offer_type": "passenger", "number_of_passengers": "4", "phone_number": "+998900689295", "created_at": "2025-06-22T01:07:34.399Z", "updated_at": "2025-06-22T01:07:34.399Z"}}, {"model": "offers.offers", "pk": 55, "fields": {"chat_id": "1974800905", "full_name": "Muhammad Nur Suxbatullayev", "delivery_address": "samarkand-tashkent", "offer_type": "passenger", "number_of_passengers": "4", "phone_number": "998900689295", "created_at": "2025-06-22T02:48:49.730Z", "updated_at": "2025-06-22T02:48:49.730Z"}}, {"model": "offers.offers", "pk": 56, "fields": {"chat_id": "1974800905", "full_name": "Muhammad Nur Suxbatullayev", "delivery_address": "tashkent-samarkand", "offer_type": "passenger", "number_of_passengers": "1", "phone_number": "+998900689295", "created_at": "2025-06-22T05:01:08.577Z", "updated_at": "2025-06-22T05:01:08.577Z"}}, {"model": "offers.offers", "pk": 57, "fields": {"chat_id": "7651092875", "full_name": "Ok", "delivery_address": "samarkand-tashkent", "offer_type": "passenger", "number_of_passengers": "1", "phone_number": "+998500049031", "created_at": "2025-06-22T06:37:18.151Z", "updated_at": "2025-06-22T06:37:18.152Z"}}, {"model": "offers.offers", "pk": 58, "fields": {"chat_id": "1976715896", "full_name": "Asadbek Allayorov", "delivery_address": "samarkand-tashkent", "offer_type": "mail", "number_of_passengers": null, "phone_number": "+988940470047", "created_at": "2025-06-22T10:16:55.527Z", "updated_at": "2025-06-22T10:16:55.527Z"}}, {"model": "offers.offers", "pk": 59, "fields": {"chat_id": "1974800905", "full_name": "Muhammad Nur Suxbatullayev", "delivery_address": "tashkent-samarkand", "offer_type": "mail", "number_of_passengers": null, "phone_number": "+998900689295", "created_at": "2025-06-23T11:01:18.334Z", "updated_at": "2025-06-23T11:01:18.334Z"}}, {"model": "offers.offers", "pk": 60, "fields": {"chat_id": "725168806", "full_name": "Рахимжон", "delivery_address": "tashkent-samarkand", "offer_type": "passenger", "number_of_passengers": "3", "phone_number": "998935365985", "created_at": "2025-06-24T06:21:44.114Z", "updated_at": "2025-06-24T06:21:44.114Z"}}, {"model": "offers.offers", "pk": 61, "fields": {"chat_id": "467185059", "full_name": "Jamshiddin", "delivery_address": "tashkent-samarkand", "offer_type": "passenger", "number_of_passengers": "4", "phone_number": "+998983130059", "created_at": "2025-06-24T11:40:34.462Z", "updated_at": "2025-06-24T11:40:34.462Z"}}, {"model": "offers.offers", "pk": 62, "fields": {"chat_id": "1974800905", "full_name": "Muhammad Nur Suxbatullayev", "delivery_address": "tashkent-samarkand", "offer_type": "passenger", "number_of_passengers": "4", "phone_number": "998900689295", "created_at": "2025-06-25T08:50:37.026Z", "updated_at": "2025-06-25T08:50:37.026Z"}}, {"model": "offers.offers", "pk": 63, "fields": {"chat_id": "725168806", "full_name": "Рахимжон", "delivery_address": "samarkand-tashkent", "offer_type": "passenger", "number_of_passengers": "4", "phone_number": "998935365985", "created_at": "2025-06-25T14:06:05.491Z", "updated_at": "2025-06-25T14:06:05.491Z"}}, {"model": "offers.offers", "pk": 64, "fields": {"chat_id": "6362840176", "full_name": "Dilshod", "delivery_address": "samarkand-tashkent", "offer_type": "passenger", "number_of_passengers": "2", "phone_number": "998949357577", "created_at": "2025-06-28T13:12:45.054Z", "updated_at": "2025-06-28T13:12:45.054Z"}}, {"model": "offers.offers", "pk": 65, "fields": {"chat_id": "725168806", "full_name": "Рахимжон", "delivery_address": "samarkand-tashkent", "offer_type": "passenger", "number_of_passengers": "2", "phone_number": "998935365985", "created_at": "2025-06-30T11:00:37.646Z", "updated_at": "2025-06-30T11:00:37.646Z"}}, {"model": "offers.offers", "pk": 66, "fields": {"chat_id": "61260346", "full_name": "Diyorkhuja Shukurov", "delivery_address": "tashkent-samarkand", "offer_type": "passenger", "number_of_passengers": "1", "phone_number": "998903299766", "created_at": "2025-06-30T13:58:29.999Z", "updated_at": "2025-06-30T13:58:29.999Z"}}, {"model": "offers.offers", "pk": 67, "fields": {"chat_id": "61260346", "full_name": "Diyorkhuja Shukurov", "delivery_address": "tashkent-samarkand", "offer_type": "mail", "number_of_passengers": null, "phone_number": "998903299766", "created_at": "2025-06-30T13:58:41.504Z", "updated_at": "2025-06-30T13:58:41.504Z"}}, {"model": "offers.offers", "pk": 68, "fields": {"chat_id": "5456074061", "full_name": "Diyor Ochilov", "delivery_address": "tashkent-samarkand", "offer_type": "passenger", "number_of_passengers": "1", "phone_number": "998940701224", "created_at": "2025-07-01T04:30:59.923Z", "updated_at": "2025-07-01T04:30:59.923Z"}}, {"model": "offers.offers", "pk": 69, "fields": {"chat_id": "5456074061", "full_name": "Diyor Ochilov", "delivery_address": "tashkent-samarkand", "offer_type": "passenger", "number_of_passengers": "1", "phone_number": "998940701224", "created_at": "2025-07-01T04:36:01.936Z", "updated_at": "2025-07-01T04:36:01.936Z"}}, {"model": "offers.offers", "pk": 70, "fields": {"chat_id": "5456074061", "full_name": "Diyor Ochilov", "delivery_address": "tashkent-samarkand", "offer_type": "passenger", "number_of_passengers": "1", "phone_number": "998940701224", "created_at": "2025-07-01T04:52:56.758Z", "updated_at": "2025-07-01T04:52:56.759Z"}}, {"model": "offers.offers", "pk": 71, "fields": {"chat_id": "6597621564", "full_name": "Юсупов Мақсуд Халмирзаевич Максуд", "delivery_address": "samarkand-tashkent", "offer_type": "passenger", "number_of_passengers": "4", "phone_number": "+998937426385", "created_at": "2025-07-01T06:14:30.762Z", "updated_at": "2025-07-01T06:14:30.762Z"}}, {"model": "offers.offers", "pk": 72, "fields": {"chat_id": "5046532768", "full_name": "A", "delivery_address": "tashkent-samarkand", "offer_type": "passenger", "number_of_passengers": "1", "phone_number": "905518488015", "created_at": "2025-07-01T13:12:02.316Z", "updated_at": "2025-07-01T13:12:02.317Z"}}, {"model": "offers.offers", "pk": 73, "fields": {"chat_id": "515007330", "full_name": "Aziz Kayumov", "delivery_address": "samarkand-tashkent", "offer_type": "passenger", "number_of_passengers": "2", "phone_number": "+998942425626", "created_at": "2025-07-02T08:20:36.646Z", "updated_at": "2025-07-02T08:20:36.646Z"}}]